{
	"parent": "builtin/entity",
	"display": {
		"thirdperson_righthand": {
			"translation": [0, 6, -7],
			"scale": [0.8, 0.8, 0.8]
		},
		"thirdperson_lefthand": {
			"translation": [0, 6, -7],
			"scale": [0.8, 0.8, 0.8]
		},
		"firstperson_righthand": {
			"translation": [-5.25, 8.25, -1],
			"scale": [0.6, 0.6, 0.6]
		},
		"firstperson_lefthand": {
			"translation": [-5.25, 8.25, -1],
			"scale": [0.6, 0.6, 0.6]
		},
		"ground": {
			"translation": [0, 7.75, -10.25]
		},
		"gui": {
			"rotation": [28, -133, 0],
			"translation": [10, 6, 0],
			"scale": [1.5, 1.5, 1.5]
		},
		"fixed": {
			"rotation": [0, 90, 0],
			"translation": [-13.25, 12.25, -3],
			"scale": [1.5, 1.5, 1.5]
		}
	}
}